yni/__init__.py
yni/addition.py
yni/header.py
yni/parser.py
yni-0.1.5.dist-info/LICENSE
yni-0.1.5.dist-info/WHEEL
yni-0.1.5.dist-info/METADATA
yni-0.1.5.dist-info/RECORD
